{
  "version": "5",
  "dialect": "mysql",
  "id": "5d548a45-e09a-4d4b-a7fe-eb212c20afa2",
  "prevId": "00000000-0000-0000-0000-000000000000",
  "tables": {
    "migrations": {
      "name": "migrations",
      "columns": {
        "id": {
          "name": "id",
          "type": "int",
          "primaryKey": false,
          "notNull": true,
          "autoincrement": true
        },
        "migration": {
          "name": "migration",
          "type": "varchar(200)",
          "primaryKey": false,
          "notNull": true,
          "autoincrement": false
        },
        "batch": {
          "name": "batch",
          "type": "int",
          "primaryKey": false,
          "notNull": true,
          "autoincrement": false
        }
      },
      "indexes": {},
      "foreignKeys": {},
      "compositePrimaryKeys": {},
      "uniqueConstraints": {},
      "checkConstraint": {}
    },
    "tec_beneficiaries": {
      "name": "tec_beneficiaries",
      "columns": {
        "id": {
          "name": "id",
          "type": "int",
          "primaryKey": false,
          "notNull": true,
          "autoincrement": true
        },
        "name": {
          "name": "name",
          "type": "varchar(50)",
          "primaryKey": false,
          "notNull": true,
          "autoincrement": false
        },
        "type": {
          "name": "type",
          "type": "varchar(50)",
          "primaryKey": false,
          "notNull": false,
          "autoincrement": false,
          "default": "'NULL'"
        }
      },
      "indexes": {},
      "foreignKeys": {},
      "compositePrimaryKeys": {},
      "uniqueConstraints": {},
      "checkConstraint": {}
    },
    "tec_beneficiary": {
      "name": "tec_beneficiary",
      "columns": {
        "id": {
          "name": "id",
          "type": "int",
          "primaryKey": false,
          "notNull": true,
          "autoincrement": true
        },
        "name": {
          "name": "name",
          "type": "varchar(50)",
          "primaryKey": false,
          "notNull": true,
          "autoincrement": false,
          "default": "''''"
        }
      },
      "indexes": {},
      "foreignKeys": {},
      "compositePrimaryKeys": {},
      "uniqueConstraints": {},
      "checkConstraint": {}
    },
    "tec_categories": {
      "name": "tec_categories",
      "columns": {
        "id": {
          "name": "id",
          "type": "int",
          "primaryKey": false,
          "notNull": true,
          "autoincrement": true
        },
        "code": {
          "name": "code",
          "type": "varchar(20)",
          "primaryKey": false,
          "notNull": true,
          "autoincrement": false
        },
        "name": {
          "name": "name",
          "type": "varchar(55)",
          "primaryKey": false,
          "notNull": true,
          "autoincrement": false
        },
        "image": {
          "name": "image",
          "type": "varchar(100)",
          "primaryKey": false,
          "notNull": false,
          "autoincrement": false,
          "default": "'''no_image.png'''"
        }
      },
      "indexes": {},
      "foreignKeys": {},
      "compositePrimaryKeys": {},
      "uniqueConstraints": {},
      "checkConstraint": {}
    },
    "tec_combo_items": {
      "name": "tec_combo_items",
      "columns": {
        "id": {
          "name": "id",
          "type": "int",
          "primaryKey": false,
          "notNull": true,
          "autoincrement": true
        },
        "product_id": {
          "name": "product_id",
          "type": "int",
          "primaryKey": false,
          "notNull": true,
          "autoincrement": false
        },
        "item_code": {
          "name": "item_code",
          "type": "varchar(20)",
          "primaryKey": false,
          "notNull": true,
          "autoincrement": false
        },
        "quantity": {
          "name": "quantity",
          "type": "decimal(12,4)",
          "primaryKey": false,
          "notNull": true,
          "autoincrement": false
        },
        "price": {
          "name": "price",
          "type": "decimal(25,4)",
          "primaryKey": false,
          "notNull": false,
          "autoincrement": false,
          "default": "'NULL'"
        },
        "cost": {
          "name": "cost",
          "type": "decimal(25,4)",
          "primaryKey": false,
          "notNull": false,
          "autoincrement": false,
          "default": "'NULL'"
        }
      },
      "indexes": {},
      "foreignKeys": {},
      "compositePrimaryKeys": {},
      "uniqueConstraints": {},
      "checkConstraint": {}
    },
    "tec_customers": {
      "name": "tec_customers",
      "columns": {
        "id": {
          "name": "id",
          "type": "int",
          "primaryKey": false,
          "notNull": true,
          "autoincrement": true
        },
        "name": {
          "name": "name",
          "type": "varchar(55)",
          "primaryKey": false,
          "notNull": true,
          "autoincrement": false
        },
        "cf1": {
          "name": "cf1",
          "type": "varchar(255)",
          "primaryKey": false,
          "notNull": true,
          "autoincrement": false
        },
        "cf2": {
          "name": "cf2",
          "type": "varchar(255)",
          "primaryKey": false,
          "notNull": true,
          "autoincrement": false
        },
        "phone": {
          "name": "phone",
          "type": "varchar(20)",
          "primaryKey": false,
          "notNull": true,
          "autoincrement": false
        },
        "email": {
          "name": "email",
          "type": "varchar(100)",
          "primaryKey": false,
          "notNull": true,
          "autoincrement": false
        },
        "store_id": {
          "name": "store_id",
          "type": "int",
          "primaryKey": false,
          "notNull": false,
          "autoincrement": false,
          "default": "'NULL'"
        },
        "montant_apayer": {
          "name": "montant_apayer",
          "type": "int",
          "primaryKey": false,
          "notNull": false,
          "autoincrement": false,
          "default": "'NULL'"
        }
      },
      "indexes": {},
      "foreignKeys": {},
      "compositePrimaryKeys": {},
      "uniqueConstraints": {},
      "checkConstraint": {}
    },
    "tec_expenses": {
      "name": "tec_expenses",
      "columns": {
        "id": {
          "name": "id",
          "type": "int",
          "primaryKey": false,
          "notNull": true,
          "autoincrement": true
        },
        "date": {
          "name": "date",
          "type": "timestamp",
          "primaryKey": false,
          "notNull": true,
          "autoincrement": false,
          "default": "'current_timestamp()'"
        },
        "reference": {
          "name": "reference",
          "type": "varchar(50)",
          "primaryKey": false,
          "notNull": true,
          "autoincrement": false
        },
        "amount": {
          "name": "amount",
          "type": "decimal(25,4)",
          "primaryKey": false,
          "notNull": true,
          "autoincrement": false
        },
        "note": {
          "name": "note",
          "type": "varchar(1000)",
          "primaryKey": false,
          "notNull": false,
          "autoincrement": false,
          "default": "'NULL'"
        },
        "created_by": {
          "name": "created_by",
          "type": "varchar(55)",
          "primaryKey": false,
          "notNull": true,
          "autoincrement": false
        },
        "attachment": {
          "name": "attachment",
          "type": "varchar(55)",
          "primaryKey": false,
          "notNull": false,
          "autoincrement": false,
          "default": "'NULL'"
        },
        "store_id": {
          "name": "store_id",
          "type": "int",
          "primaryKey": false,
          "notNull": true,
          "autoincrement": false,
          "default": 1
        },
        "beneficiary_name": {
          "name": "beneficiary_name",
          "type": "varchar(1000)",
          "primaryKey": false,
          "notNull": false,
          "autoincrement": false,
          "default": "'NULL'"
        },
        "beneficiary_id": {
          "name": "beneficiary_id",
          "type": "int",
          "primaryKey": false,
          "notNull": true,
          "autoincrement": false
        },
        "year_id": {
          "name": "year_id",
          "type": "int",
          "primaryKey": false,
          "notNull": false,
          "autoincrement": false,
          "default": "'NULL'"
        }
      },
      "indexes": {},
      "foreignKeys": {},
      "compositePrimaryKeys": {},
      "uniqueConstraints": {},
      "checkConstraint": {}
    },
    "tec_gift_cards": {
      "name": "tec_gift_cards",
      "columns": {
        "id": {
          "name": "id",
          "type": "int",
          "primaryKey": false,
          "notNull": true,
          "autoincrement": true
        },
        "date": {
          "name": "date",
          "type": "timestamp",
          "primaryKey": false,
          "notNull": true,
          "autoincrement": false,
          "default": "'current_timestamp()'"
        },
        "card_no": {
          "name": "card_no",
          "type": "varchar(20)",
          "primaryKey": false,
          "notNull": true,
          "autoincrement": false
        },
        "value": {
          "name": "value",
          "type": "decimal(25,4)",
          "primaryKey": false,
          "notNull": true,
          "autoincrement": false
        },
        "customer_id": {
          "name": "customer_id",
          "type": "int",
          "primaryKey": false,
          "notNull": false,
          "autoincrement": false,
          "default": "'NULL'"
        },
        "balance": {
          "name": "balance",
          "type": "decimal(25,4)",
          "primaryKey": false,
          "notNull": true,
          "autoincrement": false
        },
        "expiry": {
          "name": "expiry",
          "type": "date",
          "primaryKey": false,
          "notNull": false,
          "autoincrement": false,
          "default": "'NULL'"
        },
        "created_by": {
          "name": "created_by",
          "type": "int",
          "primaryKey": false,
          "notNull": false,
          "autoincrement": false,
          "default": "'NULL'"
        },
        "store_id": {
          "name": "store_id",
          "type": "int",
          "primaryKey": false,
          "notNull": false,
          "autoincrement": false,
          "default": "'NULL'"
        }
      },
      "indexes": {},
      "foreignKeys": {},
      "compositePrimaryKeys": {},
      "uniqueConstraints": {
        "card_no": {
          "name": "card_no",
          "columns": [
            "card_no"
          ]
        }
      },
      "checkConstraint": {}
    },
    "tec_groups": {
      "name": "tec_groups",
      "columns": {
        "id": {
          "name": "id",
          "type": "mediumint",
          "primaryKey": false,
          "notNull": true,
          "autoincrement": true
        },
        "name": {
          "name": "name",
          "type": "varchar(20)",
          "primaryKey": false,
          "notNull": true,
          "autoincrement": false
        },
        "description": {
          "name": "description",
          "type": "varchar(100)",
          "primaryKey": false,
          "notNull": true,
          "autoincrement": false
        }
      },
      "indexes": {},
      "foreignKeys": {},
      "compositePrimaryKeys": {},
      "uniqueConstraints": {},
      "checkConstraint": {}
    },
    "tec_login_attempts": {
      "name": "tec_login_attempts",
      "columns": {
        "id": {
          "name": "id",
          "type": "mediumint",
          "primaryKey": false,
          "notNull": true,
          "autoincrement": true
        },
        "ip_address": {
          "name": "ip_address",
          "type": "varbinary(16)",
          "primaryKey": false,
          "notNull": true,
          "autoincrement": false
        },
        "login": {
          "name": "login",
          "type": "varchar(100)",
          "primaryKey": false,
          "notNull": true,
          "autoincrement": false
        },
        "time": {
          "name": "time",
          "type": "int",
          "primaryKey": false,
          "notNull": false,
          "autoincrement": false,
          "default": "'NULL'"
        }
      },
      "indexes": {},
      "foreignKeys": {},
      "compositePrimaryKeys": {},
      "uniqueConstraints": {},
      "checkConstraint": {}
    },
    "tec_payments": {
      "name": "tec_payments",
      "columns": {
        "id": {
          "name": "id",
          "type": "int",
          "primaryKey": false,
          "notNull": true,
          "autoincrement": true
        },
        "date": {
          "name": "date",
          "type": "timestamp",
          "primaryKey": false,
          "notNull": false,
          "autoincrement": false,
          "default": "'current_timestamp()'"
        },
        "sale_id": {
          "name": "sale_id",
          "type": "int",
          "primaryKey": false,
          "notNull": false,
          "autoincrement": false,
          "default": "'NULL'"
        },
        "customer_id": {
          "name": "customer_id",
          "type": "int",
          "primaryKey": false,
          "notNull": false,
          "autoincrement": false,
          "default": "'NULL'"
        },
        "transaction_id": {
          "name": "transaction_id",
          "type": "varchar(50)",
          "primaryKey": false,
          "notNull": false,
          "autoincrement": false,
          "default": "'NULL'"
        },
        "paid_by": {
          "name": "paid_by",
          "type": "varchar(20)",
          "primaryKey": false,
          "notNull": true,
          "autoincrement": false
        },
        "cheque_no": {
          "name": "cheque_no",
          "type": "varchar(20)",
          "primaryKey": false,
          "notNull": false,
          "autoincrement": false,
          "default": "'NULL'"
        },
        "cc_no": {
          "name": "cc_no",
          "type": "varchar(20)",
          "primaryKey": false,
          "notNull": false,
          "autoincrement": false,
          "default": "'NULL'"
        },
        "cc_holder": {
          "name": "cc_holder",
          "type": "varchar(25)",
          "primaryKey": false,
          "notNull": false,
          "autoincrement": false,
          "default": "'NULL'"
        },
        "cc_month": {
          "name": "cc_month",
          "type": "varchar(2)",
          "primaryKey": false,
          "notNull": false,
          "autoincrement": false,
          "default": "'NULL'"
        },
        "cc_year": {
          "name": "cc_year",
          "type": "varchar(4)",
          "primaryKey": false,
          "notNull": false,
          "autoincrement": false,
          "default": "'NULL'"
        },
        "cc_type": {
          "name": "cc_type",
          "type": "varchar(20)",
          "primaryKey": false,
          "notNull": false,
          "autoincrement": false,
          "default": "'NULL'"
        },
        "amount": {
          "name": "amount",
          "type": "decimal(25,4)",
          "primaryKey": false,
          "notNull": true,
          "autoincrement": false
        },
        "currency": {
          "name": "currency",
          "type": "varchar(3)",
          "primaryKey": false,
          "notNull": false,
          "autoincrement": false,
          "default": "'NULL'"
        },
        "created_by": {
          "name": "created_by",
          "type": "int",
          "primaryKey": false,
          "notNull": true,
          "autoincrement": false
        },
        "attachment": {
          "name": "attachment",
          "type": "varchar(55)",
          "primaryKey": false,
          "notNull": false,
          "autoincrement": false,
          "default": "'NULL'"
        },
        "note": {
          "name": "note",
          "type": "varchar(1000)",
          "primaryKey": false,
          "notNull": false,
          "autoincrement": false,
          "default": "'NULL'"
        },
        "pos_paid": {
          "name": "pos_paid",
          "type": "decimal(25,4)",
          "primaryKey": false,
          "notNull": false,
          "autoincrement": false,
          "default": "'0.0000'"
        },
        "pos_balance": {
          "name": "pos_balance",
          "type": "decimal(25,4)",
          "primaryKey": false,
          "notNull": false,
          "autoincrement": false,
          "default": "'0.0000'"
        },
        "gc_no": {
          "name": "gc_no",
          "type": "varchar(20)",
          "primaryKey": false,
          "notNull": false,
          "autoincrement": false,
          "default": "'NULL'"
        },
        "reference": {
          "name": "reference",
          "type": "varchar(50)",
          "primaryKey": false,
          "notNull": false,
          "autoincrement": false,
          "default": "'NULL'"
        },
        "updated_by": {
          "name": "updated_by",
          "type": "int",
          "primaryKey": false,
          "notNull": false,
          "autoincrement": false,
          "default": "'NULL'"
        },
        "updated_at": {
          "name": "updated_at",
          "type": "timestamp",
          "primaryKey": false,
          "notNull": false,
          "autoincrement": false,
          "default": "'NULL'"
        },
        "store_id": {
          "name": "store_id",
          "type": "int",
          "primaryKey": false,
          "notNull": true,
          "autoincrement": false,
          "default": 1
        }
      },
      "indexes": {},
      "foreignKeys": {},
      "compositePrimaryKeys": {},
      "uniqueConstraints": {},
      "checkConstraint": {}
    },
    "tec_printers": {
      "name": "tec_printers",
      "columns": {
        "id": {
          "name": "id",
          "type": "int",
          "primaryKey": false,
          "notNull": true,
          "autoincrement": true
        },
        "title": {
          "name": "title",
          "type": "varchar(55)",
          "primaryKey": false,
          "notNull": true,
          "autoincrement": false
        },
        "type": {
          "name": "type",
          "type": "varchar(25)",
          "primaryKey": false,
          "notNull": true,
          "autoincrement": false
        },
        "profile": {
          "name": "profile",
          "type": "varchar(25)",
          "primaryKey": false,
          "notNull": true,
          "autoincrement": false
        },
        "char_per_line": {
          "name": "char_per_line",
          "type": "tinyint",
          "primaryKey": false,
          "notNull": false,
          "autoincrement": false,
          "default": "'NULL'"
        },
        "path": {
          "name": "path",
          "type": "varchar(255)",
          "primaryKey": false,
          "notNull": false,
          "autoincrement": false,
          "default": "'NULL'"
        },
        "ip_address": {
          "name": "ip_address",
          "type": "varbinary(45)",
          "primaryKey": false,
          "notNull": false,
          "autoincrement": false,
          "default": "'NULL'"
        },
        "port": {
          "name": "port",
          "type": "varchar(10)",
          "primaryKey": false,
          "notNull": false,
          "autoincrement": false,
          "default": "'NULL'"
        }
      },
      "indexes": {},
      "foreignKeys": {},
      "compositePrimaryKeys": {},
      "uniqueConstraints": {},
      "checkConstraint": {}
    },
    "tec_product_store_qty": {
      "name": "tec_product_store_qty",
      "columns": {
        "id": {
          "name": "id",
          "type": "int",
          "primaryKey": false,
          "notNull": true,
          "autoincrement": true
        },
        "product_id": {
          "name": "product_id",
          "type": "int",
          "primaryKey": false,
          "notNull": true,
          "autoincrement": false
        },
        "store_id": {
          "name": "store_id",
          "type": "int",
          "primaryKey": false,
          "notNull": true,
          "autoincrement": false
        },
        "quantity": {
          "name": "quantity",
          "type": "decimal(15,4)",
          "primaryKey": false,
          "notNull": true,
          "autoincrement": false,
          "default": "'0.0000'"
        },
        "price": {
          "name": "price",
          "type": "decimal(25,4)",
          "primaryKey": false,
          "notNull": false,
          "autoincrement": false,
          "default": "'NULL'"
        }
      },
      "indexes": {
        "product_id": {
          "name": "product_id",
          "columns": [
            "product_id"
          ],
          "isUnique": false
        },
        "store_id": {
          "name": "store_id",
          "columns": [
            "store_id"
          ],
          "isUnique": false
        }
      },
      "foreignKeys": {},
      "compositePrimaryKeys": {},
      "uniqueConstraints": {},
      "checkConstraint": {}
    },
    "tec_products": {
      "name": "tec_products",
      "columns": {
        "id": {
          "name": "id",
          "type": "int",
          "primaryKey": false,
          "notNull": true,
          "autoincrement": true
        },
        "code": {
          "name": "code",
          "type": "varchar(50)",
          "primaryKey": false,
          "notNull": true,
          "autoincrement": false
        },
        "name": {
          "name": "name",
          "type": "char(255)",
          "primaryKey": false,
          "notNull": true,
          "autoincrement": false
        },
        "category_id": {
          "name": "category_id",
          "type": "int",
          "primaryKey": false,
          "notNull": true,
          "autoincrement": false,
          "default": 1
        },
        "price": {
          "name": "price",
          "type": "decimal(25,4)",
          "primaryKey": false,
          "notNull": true,
          "autoincrement": false
        },
        "image": {
          "name": "image",
          "type": "varchar(255)",
          "primaryKey": false,
          "notNull": false,
          "autoincrement": false,
          "default": "'''no_image.png'''"
        },
        "tax": {
          "name": "tax",
          "type": "varchar(20)",
          "primaryKey": false,
          "notNull": false,
          "autoincrement": false,
          "default": "'NULL'"
        },
        "cost": {
          "name": "cost",
          "type": "decimal(25,4)",
          "primaryKey": false,
          "notNull": false,
          "autoincrement": false,
          "default": "'NULL'"
        },
        "tax_method": {
          "name": "tax_method",
          "type": "tinyint",
          "primaryKey": false,
          "notNull": false,
          "autoincrement": false,
          "default": 1
        },
        "quantity": {
          "name": "quantity",
          "type": "decimal(15,4)",
          "primaryKey": false,
          "notNull": false,
          "autoincrement": false,
          "default": "'0.0000'"
        },
        "barcode_symbology": {
          "name": "barcode_symbology",
          "type": "varchar(20)",
          "primaryKey": false,
          "notNull": true,
          "autoincrement": false,
          "default": "'''code39'''"
        },
        "type": {
          "name": "type",
          "type": "varchar(20)",
          "primaryKey": false,
          "notNull": true,
          "autoincrement": false,
          "default": "'''standard'''"
        },
        "details": {
          "name": "details",
          "type": "text",
          "primaryKey": false,
          "notNull": false,
          "autoincrement": false,
          "default": "('NULL')"
        },
        "alert_quantity": {
          "name": "alert_quantity",
          "type": "decimal(10,4)",
          "primaryKey": false,
          "notNull": false,
          "autoincrement": false,
          "default": "'0.0000'"
        },
        "year_id": {
          "name": "year_id",
          "type": "int",
          "primaryKey": false,
          "notNull": false,
          "autoincrement": false,
          "default": "'NULL'"
        }
      },
      "indexes": {},
      "foreignKeys": {},
      "compositePrimaryKeys": {},
      "uniqueConstraints": {
        "code": {
          "name": "code",
          "columns": [
            "code"
          ]
        }
      },
      "checkConstraint": {}
    },
    "tec_purchase_items": {
      "name": "tec_purchase_items",
      "columns": {
        "id": {
          "name": "id",
          "type": "int",
          "primaryKey": false,
          "notNull": true,
          "autoincrement": true
        },
        "purchase_id": {
          "name": "purchase_id",
          "type": "int",
          "primaryKey": false,
          "notNull": true,
          "autoincrement": false
        },
        "product_id": {
          "name": "product_id",
          "type": "int",
          "primaryKey": false,
          "notNull": true,
          "autoincrement": false
        },
        "quantity": {
          "name": "quantity",
          "type": "decimal(15,4)",
          "primaryKey": false,
          "notNull": true,
          "autoincrement": false
        },
        "cost": {
          "name": "cost",
          "type": "decimal(25,4)",
          "primaryKey": false,
          "notNull": true,
          "autoincrement": false
        },
        "subtotal": {
          "name": "subtotal",
          "type": "decimal(25,4)",
          "primaryKey": false,
          "notNull": true,
          "autoincrement": false
        }
      },
      "indexes": {},
      "foreignKeys": {},
      "compositePrimaryKeys": {},
      "uniqueConstraints": {},
      "checkConstraint": {}
    },
    "tec_purchases": {
      "name": "tec_purchases",
      "columns": {
        "id": {
          "name": "id",
          "type": "int",
          "primaryKey": false,
          "notNull": true,
          "autoincrement": true
        },
        "reference": {
          "name": "reference",
          "type": "varchar(55)",
          "primaryKey": false,
          "notNull": true,
          "autoincrement": false
        },
        "date": {
          "name": "date",
          "type": "timestamp",
          "primaryKey": false,
          "notNull": true,
          "autoincrement": false,
          "default": "'current_timestamp()'"
        },
        "note": {
          "name": "note",
          "type": "varchar(1000)",
          "primaryKey": false,
          "notNull": true,
          "autoincrement": false
        },
        "total": {
          "name": "total",
          "type": "decimal(25,4)",
          "primaryKey": false,
          "notNull": true,
          "autoincrement": false
        },
        "attachment": {
          "name": "attachment",
          "type": "varchar(255)",
          "primaryKey": false,
          "notNull": false,
          "autoincrement": false,
          "default": "'NULL'"
        },
        "supplier_id": {
          "name": "supplier_id",
          "type": "int",
          "primaryKey": false,
          "notNull": false,
          "autoincrement": false,
          "default": "'NULL'"
        },
        "received": {
          "name": "received",
          "type": "tinyint",
          "primaryKey": false,
          "notNull": false,
          "autoincrement": false,
          "default": "'NULL'"
        },
        "created_by": {
          "name": "created_by",
          "type": "int",
          "primaryKey": false,
          "notNull": true,
          "autoincrement": false
        },
        "store_id": {
          "name": "store_id",
          "type": "int",
          "primaryKey": false,
          "notNull": true,
          "autoincrement": false,
          "default": 1
        }
      },
      "indexes": {},
      "foreignKeys": {},
      "compositePrimaryKeys": {},
      "uniqueConstraints": {},
      "checkConstraint": {}
    },
    "tec_registers": {
      "name": "tec_registers",
      "columns": {
        "id": {
          "name": "id",
          "type": "int",
          "primaryKey": false,
          "notNull": true,
          "autoincrement": true
        },
        "date": {
          "name": "date",
          "type": "timestamp",
          "primaryKey": false,
          "notNull": true,
          "autoincrement": false,
          "default": "'current_timestamp()'"
        },
        "user_id": {
          "name": "user_id",
          "type": "int",
          "primaryKey": false,
          "notNull": true,
          "autoincrement": false
        },
        "cash_in_hand": {
          "name": "cash_in_hand",
          "type": "decimal(25,4)",
          "primaryKey": false,
          "notNull": true,
          "autoincrement": false
        },
        "status": {
          "name": "status",
          "type": "varchar(10)",
          "primaryKey": false,
          "notNull": true,
          "autoincrement": false
        },
        "total_cash": {
          "name": "total_cash",
          "type": "decimal(25,4)",
          "primaryKey": false,
          "notNull": false,
          "autoincrement": false,
          "default": "'NULL'"
        },
        "total_cheques": {
          "name": "total_cheques",
          "type": "int",
          "primaryKey": false,
          "notNull": false,
          "autoincrement": false,
          "default": "'NULL'"
        },
        "total_cc_slips": {
          "name": "total_cc_slips",
          "type": "int",
          "primaryKey": false,
          "notNull": false,
          "autoincrement": false,
          "default": "'NULL'"
        },
        "total_cash_submitted": {
          "name": "total_cash_submitted",
          "type": "decimal(25,4)",
          "primaryKey": false,
          "notNull": false,
          "autoincrement": false,
          "default": "'NULL'"
        },
        "total_cheques_submitted": {
          "name": "total_cheques_submitted",
          "type": "int",
          "primaryKey": false,
          "notNull": false,
          "autoincrement": false,
          "default": "'NULL'"
        },
        "total_cc_slips_submitted": {
          "name": "total_cc_slips_submitted",
          "type": "int",
          "primaryKey": false,
          "notNull": false,
          "autoincrement": false,
          "default": "'NULL'"
        },
        "note": {
          "name": "note",
          "type": "text",
          "primaryKey": false,
          "notNull": false,
          "autoincrement": false,
          "default": "('NULL')"
        },
        "closed_at": {
          "name": "closed_at",
          "type": "timestamp",
          "primaryKey": false,
          "notNull": false,
          "autoincrement": false,
          "default": "'NULL'"
        },
        "transfer_opened_bills": {
          "name": "transfer_opened_bills",
          "type": "varchar(50)",
          "primaryKey": false,
          "notNull": false,
          "autoincrement": false,
          "default": "'NULL'"
        },
        "closed_by": {
          "name": "closed_by",
          "type": "int",
          "primaryKey": false,
          "notNull": false,
          "autoincrement": false,
          "default": "'NULL'"
        },
        "store_id": {
          "name": "store_id",
          "type": "int",
          "primaryKey": false,
          "notNull": true,
          "autoincrement": false,
          "default": 1
        }
      },
      "indexes": {},
      "foreignKeys": {},
      "compositePrimaryKeys": {},
      "uniqueConstraints": {},
      "checkConstraint": {}
    },
    "tec_sale_items": {
      "name": "tec_sale_items",
      "columns": {
        "id": {
          "name": "id",
          "type": "int",
          "primaryKey": false,
          "notNull": true,
          "autoincrement": true
        },
        "sale_id": {
          "name": "sale_id",
          "type": "int",
          "primaryKey": false,
          "notNull": true,
          "autoincrement": false
        },
        "product_id": {
          "name": "product_id",
          "type": "int",
          "primaryKey": false,
          "notNull": true,
          "autoincrement": false
        },
        "quantity": {
          "name": "quantity",
          "type": "decimal(15,4)",
          "primaryKey": false,
          "notNull": true,
          "autoincrement": false
        },
        "unit_price": {
          "name": "unit_price",
          "type": "decimal(25,4)",
          "primaryKey": false,
          "notNull": true,
          "autoincrement": false
        },
        "net_unit_price": {
          "name": "net_unit_price",
          "type": "decimal(25,4)",
          "primaryKey": false,
          "notNull": true,
          "autoincrement": false
        },
        "discount": {
          "name": "discount",
          "type": "varchar(20)",
          "primaryKey": false,
          "notNull": false,
          "autoincrement": false,
          "default": "'NULL'"
        },
        "item_discount": {
          "name": "item_discount",
          "type": "decimal(25,4)",
          "primaryKey": false,
          "notNull": false,
          "autoincrement": false,
          "default": "'NULL'"
        },
        "tax": {
          "name": "tax",
          "type": "int",
          "primaryKey": false,
          "notNull": false,
          "autoincrement": false
        },
        "item_tax": {
          "name": "item_tax",
          "type": "decimal(25,4)",
          "primaryKey": false,
          "notNull": false,
          "autoincrement": false,
          "default": "'NULL'"
        },
        "subtotal": {
          "name": "subtotal",
          "type": "decimal(25,4)",
          "primaryKey": false,
          "notNull": true,
          "autoincrement": false
        },
        "real_unit_price": {
          "name": "real_unit_price",
          "type": "decimal(25,4)",
          "primaryKey": false,
          "notNull": false,
          "autoincrement": false,
          "default": "'NULL'"
        },
        "cost": {
          "name": "cost",
          "type": "decimal(25,4)",
          "primaryKey": false,
          "notNull": false,
          "autoincrement": false,
          "default": "'0.0000'"
        },
        "product_code": {
          "name": "product_code",
          "type": "varchar(50)",
          "primaryKey": false,
          "notNull": false,
          "autoincrement": false,
          "default": "'NULL'"
        },
        "product_name": {
          "name": "product_name",
          "type": "varchar(50)",
          "primaryKey": false,
          "notNull": false,
          "autoincrement": false,
          "default": "'NULL'"
        },
        "comment": {
          "name": "comment",
          "type": "varchar(255)",
          "primaryKey": false,
          "notNull": false,
          "autoincrement": false,
          "default": "'NULL'"
        }
      },
      "indexes": {},
      "foreignKeys": {},
      "compositePrimaryKeys": {},
      "uniqueConstraints": {},
      "checkConstraint": {}
    },
    "tec_sales": {
      "name": "tec_sales",
      "columns": {
        "id": {
          "name": "id",
          "type": "int",
          "primaryKey": false,
          "notNull": true,
          "autoincrement": true
        },
        "date": {
          "name": "date",
          "type": "datetime",
          "primaryKey": false,
          "notNull": true,
          "autoincrement": false
        },
        "customer_id": {
          "name": "customer_id",
          "type": "int",
          "primaryKey": false,
          "notNull": true,
          "autoincrement": false
        },
        "customer_name": {
          "name": "customer_name",
          "type": "varchar(55)",
          "primaryKey": false,
          "notNull": true,
          "autoincrement": false
        },
        "total": {
          "name": "total",
          "type": "decimal(25,4)",
          "primaryKey": false,
          "notNull": true,
          "autoincrement": false
        },
        "product_discount": {
          "name": "product_discount",
          "type": "decimal(25,4)",
          "primaryKey": false,
          "notNull": false,
          "autoincrement": false,
          "default": "'NULL'"
        },
        "order_discount_id": {
          "name": "order_discount_id",
          "type": "varchar(20)",
          "primaryKey": false,
          "notNull": false,
          "autoincrement": false,
          "default": "'NULL'"
        },
        "order_discount": {
          "name": "order_discount",
          "type": "decimal(25,4)",
          "primaryKey": false,
          "notNull": false,
          "autoincrement": false,
          "default": "'NULL'"
        },
        "total_discount": {
          "name": "total_discount",
          "type": "decimal(25,4)",
          "primaryKey": false,
          "notNull": false,
          "autoincrement": false,
          "default": "'NULL'"
        },
        "product_tax": {
          "name": "product_tax",
          "type": "decimal(25,4)",
          "primaryKey": false,
          "notNull": false,
          "autoincrement": false,
          "default": "'NULL'"
        },
        "order_tax_id": {
          "name": "order_tax_id",
          "type": "varchar(20)",
          "primaryKey": false,
          "notNull": false,
          "autoincrement": false,
          "default": "'NULL'"
        },
        "order_tax": {
          "name": "order_tax",
          "type": "decimal(25,4)",
          "primaryKey": false,
          "notNull": false,
          "autoincrement": false,
          "default": "'NULL'"
        },
        "total_tax": {
          "name": "total_tax",
          "type": "decimal(25,4)",
          "primaryKey": false,
          "notNull": false,
          "autoincrement": false,
          "default": "'NULL'"
        },
        "grand_total": {
          "name": "grand_total",
          "type": "decimal(25,4)",
          "primaryKey": false,
          "notNull": true,
          "autoincrement": false
        },
        "total_items": {
          "name": "total_items",
          "type": "int",
          "primaryKey": false,
          "notNull": false,
          "autoincrement": false,
          "default": "'NULL'"
        },
        "total_quantity": {
          "name": "total_quantity",
          "type": "decimal(15,4)",
          "primaryKey": false,
          "notNull": false,
          "autoincrement": false,
          "default": "'NULL'"
        },
        "paid": {
          "name": "paid",
          "type": "decimal(25,4)",
          "primaryKey": false,
          "notNull": false,
          "autoincrement": false,
          "default": "'NULL'"
        },
        "created_by": {
          "name": "created_by",
          "type": "int",
          "primaryKey": false,
          "notNull": false,
          "autoincrement": false,
          "default": "'NULL'"
        },
        "updated_by": {
          "name": "updated_by",
          "type": "int",
          "primaryKey": false,
          "notNull": false,
          "autoincrement": false,
          "default": "'NULL'"
        },
        "updated_at": {
          "name": "updated_at",
          "type": "datetime",
          "primaryKey": false,
          "notNull": false,
          "autoincrement": false,
          "default": "'NULL'"
        },
        "note": {
          "name": "note",
          "type": "varchar(1000)",
          "primaryKey": false,
          "notNull": false,
          "autoincrement": false,
          "default": "'NULL'"
        },
        "status": {
          "name": "status",
          "type": "varchar(20)",
          "primaryKey": false,
          "notNull": false,
          "autoincrement": false,
          "default": "'NULL'"
        },
        "rounding": {
          "name": "rounding",
          "type": "decimal(10,4)",
          "primaryKey": false,
          "notNull": false,
          "autoincrement": false,
          "default": "'NULL'"
        },
        "store_id": {
          "name": "store_id",
          "type": "int",
          "primaryKey": false,
          "notNull": true,
          "autoincrement": false,
          "default": 1
        },
        "hold_ref": {
          "name": "hold_ref",
          "type": "varchar(255)",
          "primaryKey": false,
          "notNull": false,
          "autoincrement": false,
          "default": "'NULL'"
        }
      },
      "indexes": {},
      "foreignKeys": {
        "tec_sales_customer_id_tec_customers_id_fk": {
          "name": "tec_sales_customer_id_tec_customers_id_fk",
          "tableFrom": "tec_sales",
          "tableTo": "tec_customers",
          "columnsFrom": [
            "customer_id"
          ],
          "columnsTo": [
            "id"
          ],
          "onDelete": "restrict",
          "onUpdate": "restrict"
        }
      },
      "compositePrimaryKeys": {},
      "uniqueConstraints": {},
      "checkConstraint": {}
    },
    "tec_sessions": {
      "name": "tec_sessions",
      "columns": {
        "id": {
          "name": "id",
          "type": "varchar(40)",
          "primaryKey": false,
          "notNull": true,
          "autoincrement": false
        },
        "ip_address": {
          "name": "ip_address",
          "type": "varchar(45)",
          "primaryKey": false,
          "notNull": true,
          "autoincrement": false
        },
        "timestamp": {
          "name": "timestamp",
          "type": "int",
          "primaryKey": false,
          "notNull": true,
          "autoincrement": false,
          "default": 0
        }
      },
      "indexes": {
        "ci_sessions_timestamp": {
          "name": "ci_sessions_timestamp",
          "columns": [
            "timestamp"
          ],
          "isUnique": false
        }
      },
      "foreignKeys": {},
      "compositePrimaryKeys": {},
      "uniqueConstraints": {},
      "checkConstraint": {}
    },
    "tec_settings": {
      "name": "tec_settings",
      "columns": {
        "setting_id": {
          "name": "setting_id",
          "type": "int",
          "primaryKey": false,
          "notNull": true,
          "autoincrement": false
        },
        "logo": {
          "name": "logo",
          "type": "varchar(255)",
          "primaryKey": false,
          "notNull": true,
          "autoincrement": false
        },
        "site_name": {
          "name": "site_name",
          "type": "varchar(55)",
          "primaryKey": false,
          "notNull": true,
          "autoincrement": false
        },
        "tel": {
          "name": "tel",
          "type": "varchar(20)",
          "primaryKey": false,
          "notNull": true,
          "autoincrement": false
        },
        "dateformat": {
          "name": "dateformat",
          "type": "varchar(20)",
          "primaryKey": false,
          "notNull": false,
          "autoincrement": false,
          "default": "'NULL'"
        },
        "timeformat": {
          "name": "timeformat",
          "type": "varchar(20)",
          "primaryKey": false,
          "notNull": false,
          "autoincrement": false,
          "default": "'NULL'"
        },
        "default_email": {
          "name": "default_email",
          "type": "varchar(100)",
          "primaryKey": false,
          "notNull": true,
          "autoincrement": false
        },
        "language": {
          "name": "language",
          "type": "varchar(20)",
          "primaryKey": false,
          "notNull": true,
          "autoincrement": false
        },
        "version": {
          "name": "version",
          "type": "varchar(10)",
          "primaryKey": false,
          "notNull": true,
          "autoincrement": false,
          "default": "'''1.0'''"
        },
        "theme": {
          "name": "theme",
          "type": "varchar(20)",
          "primaryKey": false,
          "notNull": true,
          "autoincrement": false
        },
        "timezone": {
          "name": "timezone",
          "type": "varchar(255)",
          "primaryKey": false,
          "notNull": true,
          "autoincrement": false,
          "default": "'''0'''"
        },
        "protocol": {
          "name": "protocol",
          "type": "varchar(20)",
          "primaryKey": false,
          "notNull": true,
          "autoincrement": false,
          "default": "'''mail'''"
        },
        "smtp_host": {
          "name": "smtp_host",
          "type": "varchar(255)",
          "primaryKey": false,
          "notNull": false,
          "autoincrement": false,
          "default": "'NULL'"
        },
        "smtp_user": {
          "name": "smtp_user",
          "type": "varchar(100)",
          "primaryKey": false,
          "notNull": false,
          "autoincrement": false,
          "default": "'NULL'"
        },
        "smtp_pass": {
          "name": "smtp_pass",
          "type": "varchar(255)",
          "primaryKey": false,
          "notNull": false,
          "autoincrement": false,
          "default": "'NULL'"
        },
        "smtp_port": {
          "name": "smtp_port",
          "type": "varchar(10)",
          "primaryKey": false,
          "notNull": false,
          "autoincrement": false,
          "default": "'''25'''"
        },
        "smtp_crypto": {
          "name": "smtp_crypto",
          "type": "varchar(5)",
          "primaryKey": false,
          "notNull": false,
          "autoincrement": false,
          "default": "'NULL'"
        },
        "mmode": {
          "name": "mmode",
          "type": "tinyint",
          "primaryKey": false,
          "notNull": true,
          "autoincrement": false
        },
        "captcha": {
          "name": "captcha",
          "type": "tinyint",
          "primaryKey": false,
          "notNull": true,
          "autoincrement": false,
          "default": 1
        },
        "mailpath": {
          "name": "mailpath",
          "type": "varchar(55)",
          "primaryKey": false,
          "notNull": false,
          "autoincrement": false,
          "default": "'NULL'"
        },
        "currency_prefix": {
          "name": "currency_prefix",
          "type": "varchar(3)",
          "primaryKey": false,
          "notNull": true,
          "autoincrement": false
        },
        "default_customer": {
          "name": "default_customer",
          "type": "int",
          "primaryKey": false,
          "notNull": true,
          "autoincrement": false
        },
        "default_tax_rate": {
          "name": "default_tax_rate",
          "type": "varchar(20)",
          "primaryKey": false,
          "notNull": true,
          "autoincrement": false
        },
        "rows_per_page": {
          "name": "rows_per_page",
          "type": "int",
          "primaryKey": false,
          "notNull": true,
          "autoincrement": false
        },
        "total_rows": {
          "name": "total_rows",
          "type": "int",
          "primaryKey": false,
          "notNull": true,
          "autoincrement": false
        },
        "header": {
          "name": "header",
          "type": "varchar(1000)",
          "primaryKey": false,
          "notNull": false,
          "autoincrement": false,
          "default": "'NULL'"
        },
        "footer": {
          "name": "footer",
          "type": "varchar(1000)",
          "primaryKey": false,
          "notNull": false,
          "autoincrement": false,
          "default": "'NULL'"
        },
        "bsty": {
          "name": "bsty",
          "type": "tinyint",
          "primaryKey": false,
          "notNull": true,
          "autoincrement": false
        },
        "display_kb": {
          "name": "display_kb",
          "type": "tinyint",
          "primaryKey": false,
          "notNull": true,
          "autoincrement": false
        },
        "default_category": {
          "name": "default_category",
          "type": "int",
          "primaryKey": false,
          "notNull": true,
          "autoincrement": false
        },
        "default_discount": {
          "name": "default_discount",
          "type": "varchar(20)",
          "primaryKey": false,
          "notNull": true,
          "autoincrement": false
        },
        "item_addition": {
          "name": "item_addition",
          "type": "tinyint",
          "primaryKey": false,
          "notNull": true,
          "autoincrement": false
        },
        "barcode_symbology": {
          "name": "barcode_symbology",
          "type": "varchar(55)",
          "primaryKey": false,
          "notNull": false,
          "autoincrement": false,
          "default": "'NULL'"
        },
        "pro_limit": {
          "name": "pro_limit",
          "type": "tinyint",
          "primaryKey": false,
          "notNull": true,
          "autoincrement": false
        },
        "decimals": {
          "name": "decimals",
          "type": "tinyint",
          "primaryKey": false,
          "notNull": true,
          "autoincrement": false,
          "default": 2
        },
        "thousands_sep": {
          "name": "thousands_sep",
          "type": "varchar(2)",
          "primaryKey": false,
          "notNull": true,
          "autoincrement": false,
          "default": "''','''"
        },
        "decimals_sep": {
          "name": "decimals_sep",
          "type": "varchar(2)",
          "primaryKey": false,
          "notNull": true,
          "autoincrement": false,
          "default": "'''.'''"
        },
        "focus_add_item": {
          "name": "focus_add_item",
          "type": "varchar(55)",
          "primaryKey": false,
          "notNull": false,
          "autoincrement": false,
          "default": "'NULL'"
        },
        "add_customer": {
          "name": "add_customer",
          "type": "varchar(55)",
          "primaryKey": false,
          "notNull": false,
          "autoincrement": false,
          "default": "'NULL'"
        },
        "toggle_category_slider": {
          "name": "toggle_category_slider",
          "type": "varchar(55)",
          "primaryKey": false,
          "notNull": false,
          "autoincrement": false,
          "default": "'NULL'"
        },
        "cancel_sale": {
          "name": "cancel_sale",
          "type": "varchar(55)",
          "primaryKey": false,
          "notNull": false,
          "autoincrement": false,
          "default": "'NULL'"
        },
        "suspend_sale": {
          "name": "suspend_sale",
          "type": "varchar(55)",
          "primaryKey": false,
          "notNull": false,
          "autoincrement": false,
          "default": "'NULL'"
        },
        "print_order": {
          "name": "print_order",
          "type": "varchar(55)",
          "primaryKey": false,
          "notNull": false,
          "autoincrement": false,
          "default": "'NULL'"
        },
        "print_bill": {
          "name": "print_bill",
          "type": "varchar(55)",
          "primaryKey": false,
          "notNull": false,
          "autoincrement": false,
          "default": "'NULL'"
        },
        "finalize_sale": {
          "name": "finalize_sale",
          "type": "varchar(55)",
          "primaryKey": false,
          "notNull": false,
          "autoincrement": false,
          "default": "'NULL'"
        },
        "today_sale": {
          "name": "today_sale",
          "type": "varchar(55)",
          "primaryKey": false,
          "notNull": false,
          "autoincrement": false,
          "default": "'NULL'"
        },
        "open_hold_bills": {
          "name": "open_hold_bills",
          "type": "varchar(55)",
          "primaryKey": false,
          "notNull": false,
          "autoincrement": false,
          "default": "'NULL'"
        },
        "close_register": {
          "name": "close_register",
          "type": "varchar(55)",
          "primaryKey": false,
          "notNull": false,
          "autoincrement": false,
          "default": "'NULL'"
        },
        "java_applet": {
          "name": "java_applet",
          "type": "tinyint",
          "primaryKey": false,
          "notNull": true,
          "autoincrement": false
        },
        "receipt_printer": {
          "name": "receipt_printer",
          "type": "varchar(55)",
          "primaryKey": false,
          "notNull": false,
          "autoincrement": false,
          "default": "'NULL'"
        },
        "pos_printers": {
          "name": "pos_printers",
          "type": "varchar(255)",
          "primaryKey": false,
          "notNull": false,
          "autoincrement": false,
          "default": "'NULL'"
        },
        "cash_drawer_codes": {
          "name": "cash_drawer_codes",
          "type": "varchar(55)",
          "primaryKey": false,
          "notNull": false,
          "autoincrement": false,
          "default": "'NULL'"
        },
        "char_per_line": {
          "name": "char_per_line",
          "type": "tinyint",
          "primaryKey": false,
          "notNull": false,
          "autoincrement": false,
          "default": 42
        },
        "rounding": {
          "name": "rounding",
          "type": "tinyint",
          "primaryKey": false,
          "notNull": false,
          "autoincrement": false,
          "default": 0
        },
        "pin_code": {
          "name": "pin_code",
          "type": "varchar(20)",
          "primaryKey": false,
          "notNull": false,
          "autoincrement": false,
          "default": "'NULL'"
        },
        "stripe": {
          "name": "stripe",
          "type": "tinyint",
          "primaryKey": false,
          "notNull": false,
          "autoincrement": false,
          "default": "'NULL'"
        },
        "stripe_secret_key": {
          "name": "stripe_secret_key",
          "type": "varchar(100)",
          "primaryKey": false,
          "notNull": false,
          "autoincrement": false,
          "default": "'NULL'"
        },
        "stripe_publishable_key": {
          "name": "stripe_publishable_key",
          "type": "varchar(100)",
          "primaryKey": false,
          "notNull": false,
          "autoincrement": false,
          "default": "'NULL'"
        },
        "purchase_code": {
          "name": "purchase_code",
          "type": "varchar(100)",
          "primaryKey": false,
          "notNull": false,
          "autoincrement": false,
          "default": "'NULL'"
        },
        "envato_username": {
          "name": "envato_username",
          "type": "varchar(50)",
          "primaryKey": false,
          "notNull": false,
          "autoincrement": false,
          "default": "'NULL'"
        },
        "theme_style": {
          "name": "theme_style",
          "type": "varchar(25)",
          "primaryKey": false,
          "notNull": false,
          "autoincrement": false,
          "default": "'''green'''"
        },
        "after_sale_page": {
          "name": "after_sale_page",
          "type": "tinyint",
          "primaryKey": false,
          "notNull": false,
          "autoincrement": false,
          "default": "'NULL'"
        },
        "overselling": {
          "name": "overselling",
          "type": "tinyint",
          "primaryKey": false,
          "notNull": false,
          "autoincrement": false,
          "default": 1
        },
        "multi_store": {
          "name": "multi_store",
          "type": "tinyint",
          "primaryKey": false,
          "notNull": false,
          "autoincrement": false,
          "default": "'NULL'"
        },
        "qty_decimals": {
          "name": "qty_decimals",
          "type": "tinyint",
          "primaryKey": false,
          "notNull": false,
          "autoincrement": false,
          "default": 2
        },
        "symbol": {
          "name": "symbol",
          "type": "varchar(55)",
          "primaryKey": false,
          "notNull": false,
          "autoincrement": false,
          "default": "'NULL'"
        },
        "sac": {
          "name": "sac",
          "type": "tinyint",
          "primaryKey": false,
          "notNull": false,
          "autoincrement": false,
          "default": 0
        },
        "display_symbol": {
          "name": "display_symbol",
          "type": "tinyint",
          "primaryKey": false,
          "notNull": false,
          "autoincrement": false,
          "default": "'NULL'"
        },
        "remote_printing": {
          "name": "remote_printing",
          "type": "tinyint",
          "primaryKey": false,
          "notNull": false,
          "autoincrement": false,
          "default": 1
        },
        "printer": {
          "name": "printer",
          "type": "int",
          "primaryKey": false,
          "notNull": false,
          "autoincrement": false,
          "default": "'NULL'"
        },
        "order_printers": {
          "name": "order_printers",
          "type": "varchar(55)",
          "primaryKey": false,
          "notNull": false,
          "autoincrement": false,
          "default": "'NULL'"
        },
        "auto_print": {
          "name": "auto_print",
          "type": "tinyint",
          "primaryKey": false,
          "notNull": false,
          "autoincrement": false,
          "default": 0
        },
        "local_printers": {
          "name": "local_printers",
          "type": "tinyint",
          "primaryKey": false,
          "notNull": false,
          "autoincrement": false,
          "default": "'NULL'"
        },
        "rtl": {
          "name": "rtl",
          "type": "tinyint",
          "primaryKey": false,
          "notNull": false,
          "autoincrement": false,
          "default": "'NULL'"
        },
        "print_img": {
          "name": "print_img",
          "type": "tinyint",
          "primaryKey": false,
          "notNull": false,
          "autoincrement": false,
          "default": "'NULL'"
        },
        "ws_barcode_type": {
          "name": "ws_barcode_type",
          "type": "varchar(10)",
          "primaryKey": false,
          "notNull": false,
          "autoincrement": false,
          "default": "'''weight'''"
        },
        "ws_barcode_chars": {
          "name": "ws_barcode_chars",
          "type": "tinyint",
          "primaryKey": false,
          "notNull": false,
          "autoincrement": false,
          "default": "'NULL'"
        },
        "flag_chars": {
          "name": "flag_chars",
          "type": "tinyint",
          "primaryKey": false,
          "notNull": false,
          "autoincrement": false,
          "default": "'NULL'"
        },
        "item_code_start": {
          "name": "item_code_start",
          "type": "tinyint",
          "primaryKey": false,
          "notNull": false,
          "autoincrement": false,
          "default": "'NULL'"
        },
        "item_code_chars": {
          "name": "item_code_chars",
          "type": "tinyint",
          "primaryKey": false,
          "notNull": false,
          "autoincrement": false,
          "default": "'NULL'"
        },
        "price_start": {
          "name": "price_start",
          "type": "tinyint",
          "primaryKey": false,
          "notNull": false,
          "autoincrement": false,
          "default": "'NULL'"
        },
        "price_chars": {
          "name": "price_chars",
          "type": "tinyint",
          "primaryKey": false,
          "notNull": false,
          "autoincrement": false,
          "default": "'NULL'"
        },
        "price_divide_by": {
          "name": "price_divide_by",
          "type": "int",
          "primaryKey": false,
          "notNull": false,
          "autoincrement": false,
          "default": "'NULL'"
        },
        "weight_start": {
          "name": "weight_start",
          "type": "tinyint",
          "primaryKey": false,
          "notNull": false,
          "autoincrement": false,
          "default": "'NULL'"
        },
        "weight_chars": {
          "name": "weight_chars",
          "type": "tinyint",
          "primaryKey": false,
          "notNull": false,
          "autoincrement": false,
          "default": "'NULL'"
        },
        "weight_divide_by": {
          "name": "weight_divide_by",
          "type": "int",
          "primaryKey": false,
          "notNull": false,
          "autoincrement": false,
          "default": "'NULL'"
        }
      },
      "indexes": {},
      "foreignKeys": {},
      "compositePrimaryKeys": {},
      "uniqueConstraints": {},
      "checkConstraint": {}
    },
    "tec_stores": {
      "name": "tec_stores",
      "columns": {
        "id": {
          "name": "id",
          "type": "int",
          "primaryKey": false,
          "notNull": true,
          "autoincrement": true
        },
        "name": {
          "name": "name",
          "type": "varchar(50)",
          "primaryKey": false,
          "notNull": true,
          "autoincrement": false
        },
        "code": {
          "name": "code",
          "type": "varchar(20)",
          "primaryKey": false,
          "notNull": true,
          "autoincrement": false
        },
        "logo": {
          "name": "logo",
          "type": "varchar(40)",
          "primaryKey": false,
          "notNull": false,
          "autoincrement": false,
          "default": "'NULL'"
        },
        "email": {
          "name": "email",
          "type": "varchar(100)",
          "primaryKey": false,
          "notNull": false,
          "autoincrement": false,
          "default": "'NULL'"
        },
        "phone": {
          "name": "phone",
          "type": "varchar(15)",
          "primaryKey": false,
          "notNull": true,
          "autoincrement": false
        },
        "address1": {
          "name": "address1",
          "type": "varchar(50)",
          "primaryKey": false,
          "notNull": false,
          "autoincrement": false,
          "default": "'NULL'"
        },
        "address2": {
          "name": "address2",
          "type": "varchar(50)",
          "primaryKey": false,
          "notNull": false,
          "autoincrement": false,
          "default": "'NULL'"
        },
        "city": {
          "name": "city",
          "type": "varchar(20)",
          "primaryKey": false,
          "notNull": false,
          "autoincrement": false,
          "default": "'NULL'"
        },
        "state": {
          "name": "state",
          "type": "varchar(20)",
          "primaryKey": false,
          "notNull": false,
          "autoincrement": false,
          "default": "'NULL'"
        },
        "postal_code": {
          "name": "postal_code",
          "type": "varchar(8)",
          "primaryKey": false,
          "notNull": false,
          "autoincrement": false,
          "default": "'NULL'"
        },
        "country": {
          "name": "country",
          "type": "varchar(25)",
          "primaryKey": false,
          "notNull": false,
          "autoincrement": false,
          "default": "'NULL'"
        },
        "currency_code": {
          "name": "currency_code",
          "type": "varchar(3)",
          "primaryKey": false,
          "notNull": false,
          "autoincrement": false,
          "default": "'NULL'"
        },
        "receipt_header": {
          "name": "receipt_header",
          "type": "text",
          "primaryKey": false,
          "notNull": false,
          "autoincrement": false,
          "default": "('NULL')"
        },
        "receipt_footer": {
          "name": "receipt_footer",
          "type": "text",
          "primaryKey": false,
          "notNull": false,
          "autoincrement": false,
          "default": "('NULL')"
        }
      },
      "indexes": {},
      "foreignKeys": {},
      "compositePrimaryKeys": {},
      "uniqueConstraints": {},
      "checkConstraint": {}
    },
    "tec_suppliers": {
      "name": "tec_suppliers",
      "columns": {
        "id": {
          "name": "id",
          "type": "int",
          "primaryKey": false,
          "notNull": true,
          "autoincrement": true
        },
        "name": {
          "name": "name",
          "type": "varchar(55)",
          "primaryKey": false,
          "notNull": true,
          "autoincrement": false
        },
        "cf1": {
          "name": "cf1",
          "type": "varchar(255)",
          "primaryKey": false,
          "notNull": true,
          "autoincrement": false
        },
        "cf2": {
          "name": "cf2",
          "type": "varchar(255)",
          "primaryKey": false,
          "notNull": true,
          "autoincrement": false
        },
        "phone": {
          "name": "phone",
          "type": "varchar(20)",
          "primaryKey": false,
          "notNull": true,
          "autoincrement": false
        },
        "email": {
          "name": "email",
          "type": "varchar(100)",
          "primaryKey": false,
          "notNull": true,
          "autoincrement": false
        }
      },
      "indexes": {},
      "foreignKeys": {},
      "compositePrimaryKeys": {},
      "uniqueConstraints": {},
      "checkConstraint": {}
    },
    "tec_suspended_items": {
      "name": "tec_suspended_items",
      "columns": {
        "id": {
          "name": "id",
          "type": "int",
          "primaryKey": false,
          "notNull": true,
          "autoincrement": true
        },
        "suspend_id": {
          "name": "suspend_id",
          "type": "int",
          "primaryKey": false,
          "notNull": true,
          "autoincrement": false
        },
        "product_id": {
          "name": "product_id",
          "type": "int",
          "primaryKey": false,
          "notNull": true,
          "autoincrement": false
        },
        "quantity": {
          "name": "quantity",
          "type": "decimal(15,4)",
          "primaryKey": false,
          "notNull": true,
          "autoincrement": false
        },
        "unit_price": {
          "name": "unit_price",
          "type": "decimal(25,4)",
          "primaryKey": false,
          "notNull": true,
          "autoincrement": false
        },
        "net_unit_price": {
          "name": "net_unit_price",
          "type": "decimal(25,4)",
          "primaryKey": false,
          "notNull": true,
          "autoincrement": false
        },
        "discount": {
          "name": "discount",
          "type": "varchar(20)",
          "primaryKey": false,
          "notNull": false,
          "autoincrement": false,
          "default": "'NULL'"
        },
        "item_discount": {
          "name": "item_discount",
          "type": "decimal(25,4)",
          "primaryKey": false,
          "notNull": false,
          "autoincrement": false,
          "default": "'NULL'"
        },
        "tax": {
          "name": "tax",
          "type": "int",
          "primaryKey": false,
          "notNull": false,
          "autoincrement": false,
          "default": "'NULL'"
        },
        "item_tax": {
          "name": "item_tax",
          "type": "decimal(25,4)",
          "primaryKey": false,
          "notNull": false,
          "autoincrement": false,
          "default": "'NULL'"
        },
        "subtotal": {
          "name": "subtotal",
          "type": "decimal(25,4)",
          "primaryKey": false,
          "notNull": true,
          "autoincrement": false
        },
        "real_unit_price": {
          "name": "real_unit_price",
          "type": "decimal(25,4)",
          "primaryKey": false,
          "notNull": false,
          "autoincrement": false,
          "default": "'NULL'"
        },
        "product_code": {
          "name": "product_code",
          "type": "varchar(50)",
          "primaryKey": false,
          "notNull": false,
          "autoincrement": false,
          "default": "'NULL'"
        },
        "product_name": {
          "name": "product_name",
          "type": "varchar(50)",
          "primaryKey": false,
          "notNull": false,
          "autoincrement": false,
          "default": "'NULL'"
        },
        "comment": {
          "name": "comment",
          "type": "varchar(255)",
          "primaryKey": false,
          "notNull": false,
          "autoincrement": false,
          "default": "'NULL'"
        }
      },
      "indexes": {},
      "foreignKeys": {},
      "compositePrimaryKeys": {},
      "uniqueConstraints": {},
      "checkConstraint": {}
    },
    "tec_suspended_sales": {
      "name": "tec_suspended_sales",
      "columns": {
        "id": {
          "name": "id",
          "type": "int",
          "primaryKey": false,
          "notNull": true,
          "autoincrement": true
        },
        "date": {
          "name": "date",
          "type": "datetime",
          "primaryKey": false,
          "notNull": true,
          "autoincrement": false
        },
        "customer_id": {
          "name": "customer_id",
          "type": "int",
          "primaryKey": false,
          "notNull": true,
          "autoincrement": false
        },
        "customer_name": {
          "name": "customer_name",
          "type": "varchar(55)",
          "primaryKey": false,
          "notNull": true,
          "autoincrement": false
        },
        "total": {
          "name": "total",
          "type": "decimal(25,4)",
          "primaryKey": false,
          "notNull": true,
          "autoincrement": false
        },
        "product_discount": {
          "name": "product_discount",
          "type": "decimal(25,4)",
          "primaryKey": false,
          "notNull": false,
          "autoincrement": false,
          "default": "'NULL'"
        },
        "order_discount_id": {
          "name": "order_discount_id",
          "type": "varchar(20)",
          "primaryKey": false,
          "notNull": false,
          "autoincrement": false,
          "default": "'NULL'"
        },
        "order_discount": {
          "name": "order_discount",
          "type": "decimal(25,4)",
          "primaryKey": false,
          "notNull": false,
          "autoincrement": false,
          "default": "'NULL'"
        },
        "total_discount": {
          "name": "total_discount",
          "type": "decimal(25,4)",
          "primaryKey": false,
          "notNull": false,
          "autoincrement": false,
          "default": "'NULL'"
        },
        "product_tax": {
          "name": "product_tax",
          "type": "decimal(25,4)",
          "primaryKey": false,
          "notNull": false,
          "autoincrement": false,
          "default": "'NULL'"
        },
        "order_tax_id": {
          "name": "order_tax_id",
          "type": "varchar(20)",
          "primaryKey": false,
          "notNull": false,
          "autoincrement": false,
          "default": "'NULL'"
        },
        "order_tax": {
          "name": "order_tax",
          "type": "decimal(25,4)",
          "primaryKey": false,
          "notNull": false,
          "autoincrement": false,
          "default": "'NULL'"
        },
        "total_tax": {
          "name": "total_tax",
          "type": "decimal(25,4)",
          "primaryKey": false,
          "notNull": false,
          "autoincrement": false,
          "default": "'NULL'"
        },
        "grand_total": {
          "name": "grand_total",
          "type": "decimal(25,4)",
          "primaryKey": false,
          "notNull": true,
          "autoincrement": false
        },
        "total_items": {
          "name": "total_items",
          "type": "int",
          "primaryKey": false,
          "notNull": false,
          "autoincrement": false,
          "default": "'NULL'"
        },
        "total_quantity": {
          "name": "total_quantity",
          "type": "decimal(15,4)",
          "primaryKey": false,
          "notNull": false,
          "autoincrement": false,
          "default": "'NULL'"
        },
        "paid": {
          "name": "paid",
          "type": "decimal(25,4)",
          "primaryKey": false,
          "notNull": false,
          "autoincrement": false,
          "default": "'NULL'"
        },
        "created_by": {
          "name": "created_by",
          "type": "int",
          "primaryKey": false,
          "notNull": false,
          "autoincrement": false,
          "default": "'NULL'"
        },
        "updated_by": {
          "name": "updated_by",
          "type": "int",
          "primaryKey": false,
          "notNull": false,
          "autoincrement": false,
          "default": "'NULL'"
        },
        "updated_at": {
          "name": "updated_at",
          "type": "datetime",
          "primaryKey": false,
          "notNull": false,
          "autoincrement": false,
          "default": "'NULL'"
        },
        "note": {
          "name": "note",
          "type": "varchar(1000)",
          "primaryKey": false,
          "notNull": false,
          "autoincrement": false,
          "default": "'NULL'"
        },
        "hold_ref": {
          "name": "hold_ref",
          "type": "varchar(255)",
          "primaryKey": false,
          "notNull": false,
          "autoincrement": false,
          "default": "'NULL'"
        },
        "store_id": {
          "name": "store_id",
          "type": "int",
          "primaryKey": false,
          "notNull": true,
          "autoincrement": false,
          "default": 1
        }
      },
      "indexes": {},
      "foreignKeys": {},
      "compositePrimaryKeys": {},
      "uniqueConstraints": {},
      "checkConstraint": {}
    },
    "tec_user_logins": {
      "name": "tec_user_logins",
      "columns": {
        "id": {
          "name": "id",
          "type": "int",
          "primaryKey": false,
          "notNull": true,
          "autoincrement": true
        },
        "user_id": {
          "name": "user_id",
          "type": "int",
          "primaryKey": false,
          "notNull": true,
          "autoincrement": false
        },
        "company_id": {
          "name": "company_id",
          "type": "int",
          "primaryKey": false,
          "notNull": false,
          "autoincrement": false,
          "default": "'NULL'"
        },
        "ip_address": {
          "name": "ip_address",
          "type": "varbinary(16)",
          "primaryKey": false,
          "notNull": true,
          "autoincrement": false
        },
        "login": {
          "name": "login",
          "type": "varchar(100)",
          "primaryKey": false,
          "notNull": true,
          "autoincrement": false
        },
        "time": {
          "name": "time",
          "type": "timestamp",
          "primaryKey": false,
          "notNull": false,
          "autoincrement": false,
          "default": "'current_timestamp()'"
        }
      },
      "indexes": {},
      "foreignKeys": {},
      "compositePrimaryKeys": {},
      "uniqueConstraints": {},
      "checkConstraint": {}
    },
    "tec_users": {
      "name": "tec_users",
      "columns": {
        "id": {
          "name": "id",
          "type": "int",
          "primaryKey": false,
          "notNull": true,
          "autoincrement": true
        },
        "last_ip_address": {
          "name": "last_ip_address",
          "type": "varbinary(45)",
          "primaryKey": false,
          "notNull": false,
          "autoincrement": false,
          "default": "'NULL'"
        },
        "ip_address": {
          "name": "ip_address",
          "type": "varbinary(45)",
          "primaryKey": false,
          "notNull": false,
          "autoincrement": false,
          "default": "'NULL'"
        },
        "username": {
          "name": "username",
          "type": "varchar(100)",
          "primaryKey": false,
          "notNull": true,
          "autoincrement": false
        },
        "password": {
          "name": "password",
          "type": "varchar(40)",
          "primaryKey": false,
          "notNull": true,
          "autoincrement": false
        },
        "salt": {
          "name": "salt",
          "type": "varchar(40)",
          "primaryKey": false,
          "notNull": false,
          "autoincrement": false,
          "default": "'NULL'"
        },
        "email": {
          "name": "email",
          "type": "varchar(100)",
          "primaryKey": false,
          "notNull": true,
          "autoincrement": false
        },
        "activation_code": {
          "name": "activation_code",
          "type": "varchar(40)",
          "primaryKey": false,
          "notNull": false,
          "autoincrement": false,
          "default": "'NULL'"
        },
        "forgotten_password_code": {
          "name": "forgotten_password_code",
          "type": "varchar(40)",
          "primaryKey": false,
          "notNull": false,
          "autoincrement": false,
          "default": "'NULL'"
        },
        "forgotten_password_time": {
          "name": "forgotten_password_time",
          "type": "int",
          "primaryKey": false,
          "notNull": false,
          "autoincrement": false,
          "default": "'NULL'"
        },
        "remember_code": {
          "name": "remember_code",
          "type": "varchar(40)",
          "primaryKey": false,
          "notNull": false,
          "autoincrement": false,
          "default": "'NULL'"
        },
        "created_on": {
          "name": "created_on",
          "type": "int",
          "primaryKey": false,
          "notNull": true,
          "autoincrement": false
        },
        "last_login": {
          "name": "last_login",
          "type": "int",
          "primaryKey": false,
          "notNull": false,
          "autoincrement": false,
          "default": "'NULL'"
        },
        "active": {
          "name": "active",
          "type": "tinyint",
          "primaryKey": false,
          "notNull": false,
          "autoincrement": false,
          "default": "'NULL'"
        },
        "first_name": {
          "name": "first_name",
          "type": "varchar(50)",
          "primaryKey": false,
          "notNull": false,
          "autoincrement": false,
          "default": "'NULL'"
        },
        "last_name": {
          "name": "last_name",
          "type": "varchar(50)",
          "primaryKey": false,
          "notNull": false,
          "autoincrement": false,
          "default": "'NULL'"
        },
        "company": {
          "name": "company",
          "type": "varchar(100)",
          "primaryKey": false,
          "notNull": false,
          "autoincrement": false,
          "default": "'NULL'"
        },
        "phone": {
          "name": "phone",
          "type": "varchar(20)",
          "primaryKey": false,
          "notNull": false,
          "autoincrement": false,
          "default": "'NULL'"
        },
        "avatar": {
          "name": "avatar",
          "type": "varchar(55)",
          "primaryKey": false,
          "notNull": false,
          "autoincrement": false,
          "default": "'NULL'"
        },
        "gender": {
          "name": "gender",
          "type": "varchar(20)",
          "primaryKey": false,
          "notNull": false,
          "autoincrement": false,
          "default": "'NULL'"
        },
        "group_id": {
          "name": "group_id",
          "type": "int",
          "primaryKey": false,
          "notNull": true,
          "autoincrement": false,
          "default": 2
        },
        "store_id": {
          "name": "store_id",
          "type": "int",
          "primaryKey": false,
          "notNull": false,
          "autoincrement": false,
          "default": "'NULL'"
        }
      },
      "indexes": {
        "group_id": {
          "name": "group_id",
          "columns": [
            "group_id"
          ],
          "isUnique": false
        }
      },
      "foreignKeys": {},
      "compositePrimaryKeys": {},
      "uniqueConstraints": {},
      "checkConstraint": {}
    },
    "tec_years": {
      "name": "tec_years",
      "columns": {
        "id": {
          "name": "id",
          "type": "int",
          "primaryKey": false,
          "notNull": true,
          "autoincrement": true
        },
        "nom_anne": {
          "name": "nom_anne",
          "type": "varchar(25)",
          "primaryKey": false,
          "notNull": true,
          "autoincrement": false
        },
        "boolen": {
          "name": "boolen",
          "type": "tinyint",
          "primaryKey": false,
          "notNull": true,
          "autoincrement": false,
          "default": 0
        }
      },
      "indexes": {},
      "foreignKeys": {},
      "compositePrimaryKeys": {},
      "uniqueConstraints": {},
      "checkConstraint": {}
    }
  },
  "views": {
    "tec_details_payments": {
      "columns": {
        "customer_id": {
          "name": "customer_id",
          "type": "int",
          "primaryKey": false,
          "notNull": true,
          "autoincrement": false
        },
        "product_name": {
          "name": "product_name",
          "type": "varchar(50)",
          "primaryKey": false,
          "notNull": false,
          "autoincrement": false,
          "default": "'NULL'"
        },
        "customer_name": {
          "name": "customer_name",
          "type": "varchar(55)",
          "primaryKey": false,
          "notNull": true,
          "autoincrement": false
        },
        "Total": {
          "name": "Total",
          "type": "decimal(40,8)",
          "primaryKey": false,
          "notNull": true,
          "autoincrement": false,
          "default": "'0.00000000'"
        },
        "date": {
          "name": "date",
          "type": "datetime",
          "primaryKey": false,
          "notNull": true,
          "autoincrement": false
        },
        "unit_price": {
          "name": "unit_price",
          "type": "decimal(25,4)",
          "primaryKey": false,
          "notNull": true,
          "autoincrement": false
        },
        "status": {
          "name": "status",
          "type": "varchar(20)",
          "primaryKey": false,
          "notNull": false,
          "autoincrement": false,
          "default": "'NULL'"
        }
      },
      "name": "tec_details_payments",
      "isExisting": false,
      "definition": "select `epim_spos`.`tec_sales`.`customer_id` AS `customer_id`,`epim_spos`.`tec_sale_items`.`product_name` AS `product_name`,`epim_spos`.`tec_sales`.`customer_name` AS `customer_name`,`epim_spos`.`tec_sale_items`.`quantity` * `epim_spos`.`tec_sale_items`.`unit_price` AS `Total`,`epim_spos`.`tec_sales`.`date` AS `date`,`epim_spos`.`tec_sale_items`.`unit_price` AS `unit_price`,`epim_spos`.`tec_sales`.`status` AS `status` from (`epim_spos`.`tec_sales` join `epim_spos`.`tec_sale_items` on(`epim_spos`.`tec_sales`.`id` = `epim_spos`.`tec_sale_items`.`sale_id`))",
      "algorithm": "undefined",
      "sqlSecurity": "definer"
    },
    "tec_salesview": {
      "columns": {
        "id": {
          "name": "id",
          "type": "int",
          "primaryKey": false,
          "notNull": true,
          "autoincrement": false,
          "default": 0
        },
        "name": {
          "name": "name",
          "type": "varchar(55)",
          "primaryKey": false,
          "notNull": true,
          "autoincrement": false
        },
        "cf1": {
          "name": "cf1",
          "type": "varchar(255)",
          "primaryKey": false,
          "notNull": true,
          "autoincrement": false
        },
        "cf2": {
          "name": "cf2",
          "type": "varchar(255)",
          "primaryKey": false,
          "notNull": true,
          "autoincrement": false
        },
        "nombre": {
          "name": "nombre",
          "type": "bigint",
          "primaryKey": false,
          "notNull": true,
          "autoincrement": false
        },
        "totals": {
          "name": "totals",
          "type": "decimal(47,4)",
          "primaryKey": false,
          "notNull": false,
          "autoincrement": false,
          "default": "'NULL'"
        },
        "montant_apayer": {
          "name": "montant_apayer",
          "type": "int",
          "primaryKey": false,
          "notNull": false,
          "autoincrement": false,
          "default": "'NULL'"
        },
        "reste": {
          "name": "reste",
          "type": "decimal(48,4)",
          "primaryKey": false,
          "notNull": false,
          "autoincrement": false,
          "default": "'NULL'"
        }
      },
      "name": "tec_salesview",
      "isExisting": false,
      "definition": "select `epim_spos`.`tec_customers`.`id` AS `id`,`epim_spos`.`tec_customers`.`name` AS `name`,`epim_spos`.`tec_customers`.`cf1` AS `cf1`,`epim_spos`.`tec_customers`.`cf2` AS `cf2`,count(0) AS `nombre`,sum(`epim_spos`.`tec_sales`.`total`) AS `totals`,`epim_spos`.`tec_customers`.`montant_apayer` AS `montant_apayer`,`epim_spos`.`tec_customers`.`montant_apayer` - sum(`epim_spos`.`tec_sales`.`total`) AS `reste` from (`epim_spos`.`tec_customers` join `epim_spos`.`tec_sales` on(`epim_spos`.`tec_sales`.`customer_id` = `epim_spos`.`tec_customers`.`id`)) where `epim_spos`.`tec_customers`.`cf1` in ('FP - TSGE','FP - TSDI','FP - TGI','FP - TI') group by `epim_spos`.`tec_customers`.`id` order by `epim_spos`.`tec_customers`.`cf1`",
      "algorithm": "undefined",
      "sqlSecurity": "definer"
    },
    "viewech": {
      "columns": {
        "id": {
          "name": "id",
          "type": "int",
          "primaryKey": false,
          "notNull": true,
          "autoincrement": false,
          "default": 0
        },
        "name": {
          "name": "name",
          "type": "varchar(55)",
          "primaryKey": false,
          "notNull": true,
          "autoincrement": false
        },
        "cf1": {
          "name": "cf1",
          "type": "varchar(255)",
          "primaryKey": false,
          "notNull": true,
          "autoincrement": false
        },
        "cf2": {
          "name": "cf2",
          "type": "varchar(255)",
          "primaryKey": false,
          "notNull": true,
          "autoincrement": false
        },
        "nombre": {
          "name": "nombre",
          "type": "bigint",
          "primaryKey": false,
          "notNull": true,
          "autoincrement": false
        },
        "totals": {
          "name": "totals",
          "type": "decimal(47,4)",
          "primaryKey": false,
          "notNull": false,
          "autoincrement": false,
          "default": "'NULL'"
        },
        "nbrEch": {
          "name": "nbrEch",
          "type": "bigint",
          "primaryKey": false,
          "notNull": true,
          "autoincrement": false
        }
      },
      "name": "viewech",
      "isExisting": false,
      "definition": "select `epim_spos`.`tec_customers`.`id` AS `id`,`epim_spos`.`tec_customers`.`name` AS `name`,`epim_spos`.`tec_customers`.`cf1` AS `cf1`,`epim_spos`.`tec_customers`.`cf2` AS `cf2`,count(0) AS `nombre`,sum(`epim_spos`.`tec_sales`.`total`) AS `totals`,count(`epim_spos`.`tec_sale_items`.`id`) AS `nbrEch` from ((`epim_spos`.`tec_customers` join `epim_spos`.`tec_sales` on(`epim_spos`.`tec_sales`.`customer_id` = `epim_spos`.`tec_customers`.`id`)) join `epim_spos`.`tec_sale_items` on(`epim_spos`.`tec_sales`.`id` = `epim_spos`.`tec_sale_items`.`sale_id`)) group by `epim_spos`.`tec_customers`.`id`",
      "algorithm": "undefined",
      "sqlSecurity": "definer"
    }
  },
  "_meta": {
    "schemas": {},
    "tables": {},
    "columns": {}
  },
  "internal": {
    "tables": {},
    "indexes": {}
  }
}